setup.py
digEmailExtractor/__init__.py
digEmailExtractor/dig_email_extractor.py
digEmailExtractor/email_extractor.py
digEmailExtractor.egg-info/PKG-INFO
digEmailExtractor.egg-info/SOURCES.txt
digEmailExtractor.egg-info/dependency_links.txt
digEmailExtractor.egg-info/requires.txt
digEmailExtractor.egg-info/top_level.txt
test/__init__.py
test/test_email_extractor.py