Metadata-Version: 1.1
Name: digEmailExtractor
Version: 0.3.1
Summary: digEmailExtractor
Home-page: https://github.com/usc-isi-i2/dig-email-extractor
Author: Lingzhe Teng
Author-email: zwein27@gmail.com
License: UNKNOWN
Download-URL: https://github.com/usc-isi-i2/dig-email-extractor
Keywords: email,extractor
Platform: UNKNOWN
